Metadata-Version: 1.1
Name: signalled-timeout
Version: 1.0.0
Summary: Timeout library for generic interruption of main thread by an exception after a configurable duration
Home-page: https://github.com/dssg/signalled-timeout
Author: Center for Data Science and Public Policy
Author-email: datascifellows@gmail.com
License: UNKNOWN
Platform: UNKNOWN
Classifier: Development Status :: 5 - Production/Stable
Classifier: Intended Audience :: Developers
Classifier: Natural Language :: English
Classifier: Programming Language :: Python :: 3.5
